liesl/__init__.py
liesl/api.py
liesl/buffers/__init__.py
liesl/buffers/blockbuffer.py
liesl/buffers/response.py
liesl/buffers/ringbuffer.py
liesl/cli/__init__.py
liesl/cli/lsl_api.py
liesl/cli/main.py
liesl/files/__init__.py
liesl/files/run.py
liesl/files/session.py
liesl/files/labrecorder/__init__.py
liesl/files/labrecorder/cli_wrapper.py
liesl/files/labrecorder/manager.py
liesl/files/labrecorder/rcc_wrapper.py
liesl/files/labrecorder/lib/LabRecorder.cfg
liesl/files/labrecorder/lib/LabRecorderCLI
liesl/files/labrecorder/lib/LabRecorderCLI.exe
liesl/files/labrecorder/lib/LabRecorderCLI_mac
liesl/files/labrecorder/lib/liblsl64.dll
liesl/files/xdf/__init__.py
liesl/files/xdf/inspect_xdf.py
liesl/files/xdf/load.py
liesl/files/xdf/manip.py
liesl/show/__init__.py
liesl/show/mpl.py
liesl/show/textplot.py
liesl/streams/__init__.py
liesl/streams/_xmltodict.py
liesl/streams/convert.py
liesl/streams/finder.py
liesl/streams/mock.py
liesl-0.3.5.0.dist-info/METADATA
liesl-0.3.5.0.dist-info/WHEEL
liesl-0.3.5.0.dist-info/entry_points.txt
liesl-0.3.5.0.dist-info/top_level.txt
liesl-0.3.5.0.dist-info/RECORD
